CalculusPy/RiemannSums.py
CalculusPy/SlopeFields.py
CalculusPy/__init__.py
tests/__init__.py
tests/test_RiemannSums.py
tests/test_SlopeFields.py
CalculusPy-1.0.6.dist-info/LICENSE
CalculusPy-1.0.6.dist-info/METADATA
CalculusPy-1.0.6.dist-info/WHEEL
CalculusPy-1.0.6.dist-info/top_level.txt
CalculusPy-1.0.6.dist-info/RECORD
