Metadata-Version: 2.1
Name: CalculusPy
Version: 1.0.6
Summary: Tool for teaching calculus in one variable.
Home-page: https://github.com/josorio398/CalculusPy_Library
Download-URL: https://github.com/josorio398/CalculusPy_Library/blob/master/CalculusPy/RiemannSums.pyy
Author: Jhonny Osorio Gallego
Author-email: osoriojohnny1986@gmail.com
License: CC BY-NC-SA 4.0
Keywords: calculus,riemann,plot,riemann sum
Classifier: Development Status :: 4 - Beta
Classifier: Intended Audience :: Developers
Classifier: Topic :: Software Development :: Build Tools
Classifier: Programming Language :: Python :: 3.4
Classifier: Programming Language :: Python :: 3.5
Classifier: Programming Language :: Python :: 3.6
Classifier: Programming Language :: Python :: 3.7
Classifier: Programming Language :: Python :: 3.8
Classifier: Programming Language :: Python :: 3.9
License-File: LICENSE
Requires-Dist: plotly (==5.11.0)
Requires-Dist: numpy
Requires-Dist: sympy
Requires-Dist: ipywidgets
